wflow/JarvisCoefficients.py
wflow/__init__.py
wflow/bmi.py
wflow/bmimodel.py
wflow/ogr2ogr.py
wflow/ops_scalar2grid.py
wflow/pcrut.py
wflow/plottss.py
wflow/reservoir_Sa.py
wflow/reservoir_Sf.py
wflow/reservoir_Si.py
wflow/reservoir_Ss.py
wflow/reservoir_Su.py
wflow/reservoir_Sw.py
wflow/rtc_wflow_bmi.py
wflow/stats.py
wflow/testrunner_wflowhbv.py
wflow/version.py
wflow/wf_DynamicFramework.py
wflow/wf_netcdfio.py
wflow/wflow_adapt.py
wflow/wflow_bmi.py
wflow/wflow_bmi_combined.py
wflow/wflow_bmi_combined_mp.py
wflow/wflow_cqf.py
wflow/wflow_delwaq.py
wflow/wflow_emwaq.py
wflow/wflow_extract.py
wflow/wflow_fit.py
wflow/wflow_fit_brute.py
wflow/wflow_floodmap.py
wflow/wflow_funcs.py
wflow/wflow_gr4.py
wflow/wflow_hbv.py
wflow/wflow_hbvl.py
wflow/wflow_lib.py
wflow/wflow_lintul.py
wflow/wflow_logging.py
wflow/wflow_obsolete.py
wflow/wflow_pcrglobwb.py
wflow/wflow_routing.py
wflow/wflow_sbm.py
wflow/wflow_sbm_old.py
wflow/wflow_sceleton.py
wflow/wflow_sediment.py
wflow/wflow_snow.py
wflow/wflow_sphy.py
wflow/wflow_stream.py
wflow/wflow_topoflex.py
wflow/wflow_upscale.py
wflow/wflow_w3.py
wflow/wflow_w3ra.py
wflow/wflow_w3ra_new.py
wflow/wflow_wave.py
wflow/pcrglobwb/__init__.py
wflow/pcrglobwb/groundwater.py
wflow/pcrglobwb/landCover.py
wflow/pcrglobwb/landSurface.py
wflow/pcrglobwb/ncConverter.py
wflow/pcrglobwb/parameterSoilAndTopo.py
wflow/pcrglobwb/routing.py
wflow/pcrglobwb/virtualOS.py
wflow/pcrglobwb/waterBodies.py
wflow/sphy/ET.py
wflow/sphy/__init__.py
wflow/sphy/advanced_routing.py
wflow/sphy/dynamic_veg.py
wflow/sphy/glacier.py
wflow/sphy/groundwater.py
wflow/sphy/hargreaves.py
wflow/sphy/lakes.py
wflow/sphy/reporting.py
wflow/sphy/reservoirs.py
wflow/sphy/rootzone.py
wflow/sphy/routing.py
wflow/sphy/snow.py
wflow/sphy/subzone.py
wflow/sphy/timecalc.py
wflow-2020.1.2.data/scripts/bmi2runner.py
wflow-2020.1.2.data/scripts/pcr2netcdf.py
wflow-2020.1.2.data/scripts/plottss.py
wflow-2020.1.2.data/scripts/tss2xml.py
wflow-2020.1.2.data/scripts/wflow_adapt.py
wflow-2020.1.2.dist-info/LICENSE
wflow-2020.1.2.dist-info/METADATA
wflow-2020.1.2.dist-info/WHEEL
wflow-2020.1.2.dist-info/top_level.txt
wflow-2020.1.2.dist-info/RECORD
