Metadata-Version: 2.1
Name: wflow
Version: 2020.1.2
Summary: wflow hydrological modeling framework
Home-page: https://wflow.readthedocs.io/
Author: J. Schellekens
Author-email: wflow@deltares.nl
License: GPL
Keywords: wflow hydrology modeling framework pcraster
Platform: UNKNOWN
Classifier: Development Status :: 5 - Production/Stable
Classifier: Intended Audience :: Developers
Classifier: Intended Audience :: Science/Research
Classifier: Topic :: Scientific/Engineering :: Hydrology
Classifier: License :: OSI Approved :: GNU General Public License v3 (GPLv3)
Classifier: Programming Language :: Python :: 3
Classifier: Programming Language :: Python :: 3.6
Classifier: Programming Language :: Python :: 3.7
Classifier: Programming Language :: Python :: 3.8
Requires-Python: >=3.6
Requires-Dist: numpy
Requires-Dist: scipy
Requires-Dist: gdal
Requires-Dist: netCDF4
Requires-Dist: xarray
Requires-Dist: cftime
Requires-Dist: numba
Requires-Dist: pyproj
Requires-Dist: python-dateutil
Provides-Extra: dev
Requires-Dist: thrift (>=0.11) ; extra == 'dev'
Requires-Dist: pyinstaller (>=3.3) ; extra == 'dev'
Requires-Dist: setuptools-scm ; extra == 'dev'
Requires-Dist: setuptools (>=38) ; extra == 'dev'
Requires-Dist: pip (>=9.0.3) ; extra == 'dev'
Requires-Dist: black ; extra == 'dev'
Requires-Dist: pylint ; extra == 'dev'
Requires-Dist: sphinx ; extra == 'dev'
Requires-Dist: sphinx-rtd-theme ; extra == 'dev'
Requires-Dist: matplotlib ; extra == 'dev'
Requires-Dist: bmi-python ; extra == 'dev'
Provides-Extra: docs
Requires-Dist: sphinx ; extra == 'docs'
Requires-Dist: sphinx-rtd-theme ; extra == 'docs'
